django_payroll_ve-0.1.0.dist-info/licenses/LICENSE
payroll/__init__.py
payroll/apps.py
payroll/conf.py
payroll/enums.py
payroll/api/serializers.py
payroll/api/urls.py
payroll/api/views.py
payroll/mgmt/commands/payroll_bootstrap_demo.py
payroll/migrations/0001_initial.py
payroll/models/component.py
payroll/models/config.py
payroll/models/employee.py
payroll/models/payslip.py
payroll/posting/adapters.py
payroll/posting/signals.py
payroll/tests/test_payroll_posting.py
payroll/utils/pdf.py
django_payroll_ve-0.1.0.dist-info/METADATA
django_payroll_ve-0.1.0.dist-info/WHEEL
django_payroll_ve-0.1.0.dist-info/top_level.txt
django_payroll_ve-0.1.0.dist-info/RECORD
