Metadata-Version: 2.4
Name: django-payroll-ve
Version: 0.1.0
Summary: Employee payroll processing and accounting integration for Django (works with django-finacc).
Author-email: "Verified Enquiries / Tushar K." <support@verifiedenquiries.com>
License: MIT
Requires-Python: >=3.11
License-File: LICENSE
Requires-Dist: Django>=5.0
Requires-Dist: djangorestframework>=3.15
Requires-Dist: django-finacc>=0.1.0
Dynamic: license-file
